debug-timer/__init__.py
debug-timer/timer.py
debug_timer/__init__.py
debug_timer-0.0.3.dist-info/METADATA
debug_timer-0.0.3.dist-info/WHEEL
debug_timer-0.0.3.dist-info/top_level.txt
debug_timer-0.0.3.dist-info/RECORD
